nonebot_plugin_exe_code/__init__.py
nonebot_plugin_exe_code/config.py
nonebot_plugin_exe_code/constant.py
nonebot_plugin_exe_code/context.py
nonebot_plugin_exe_code/exception.py
nonebot_plugin_exe_code/typings.py
nonebot_plugin_exe_code/interface/__init__.py
nonebot_plugin_exe_code/interface/api.py
nonebot_plugin_exe_code/interface/decorators.py
nonebot_plugin_exe_code/interface/group.py
nonebot_plugin_exe_code/interface/help_doc.py
nonebot_plugin_exe_code/interface/http.py
nonebot_plugin_exe_code/interface/interface.py
nonebot_plugin_exe_code/interface/user.py
nonebot_plugin_exe_code/interface/user_const_var.py
nonebot_plugin_exe_code/interface/utils.py
nonebot_plugin_exe_code/interface/adapters/__init__.py
nonebot_plugin_exe_code/interface/adapters/onebot11.py
nonebot_plugin_exe_code/interface/adapters/qq.py
nonebot_plugin_exe_code/interface/adapters/satori.py
nonebot_plugin_exe_code/interface/adapters/telegram.py
nonebot_plugin_exe_code/matchers/__init__.py
nonebot_plugin_exe_code/matchers/code.py
nonebot_plugin_exe_code/matchers/depends.py
nonebot_plugin_exe_code/matchers/getimg.py
nonebot_plugin_exe_code/matchers/getmid.py
nonebot_plugin_exe_code/matchers/getraw.py
nonebot_plugin_exe_code/matchers/terminate.py
nonebot_plugin_exe_code-1.2.0.dist-info/licenses/LICENSE
nonebot_plugin_exe_code-1.2.0.dist-info/METADATA
nonebot_plugin_exe_code-1.2.0.dist-info/WHEEL
nonebot_plugin_exe_code-1.2.0.dist-info/top_level.txt
nonebot_plugin_exe_code-1.2.0.dist-info/RECORD
