Metadata-Version: 2.4
Name: nonebot-plugin-exe-code
Version: 1.2.0
Summary: 在聊天中执行带有上下文的 Python 代码
Author-email: wyf7685 <wyf7685@163.com>
License: MIT
Project-URL: homepage, https://github.com/wyf7685/nonebot-plugin-exe-code
Project-URL: repository, https://github.com/wyf7685/nonebot-plugin-exe-code
Project-URL: documentation, https://github.com/wyf7685/nonebot-plugin-exe-code
Classifier: Programming Language :: Python :: 3
Classifier: License :: OSI Approved :: MIT License
Classifier: Operating System :: OS Independent
Requires-Python: <4.0,>=3.12
License-File: LICENSE
Requires-Dist: nonebot2>=2.4.0
Requires-Dist: nonebot-plugin-alconna>=0.57.0
Requires-Dist: nonebot-plugin-localstore>=0.7.0
Requires-Dist: nonebot-plugin-uninfo>=0.7.0
Requires-Dist: nonebot-plugin-user>=0.5.0
Requires-Dist: nonebot-plugin-waiter>=0.8.0
Requires-Dist: tarina>=0.6.1
Requires-Dist: anyio>=4.6.2.post1
Provides-Extra: pillow
Requires-Dist: Pillow; extra == "pillow"
Dynamic: license-file
